{
	"id": "getting-started/configuration",
	"title": "Configuration",
	"description": "Hoikka uses environment variables for configuration. No XML, YAML, or admin panels needed.",
	"source": "@site/docs/getting-started/configuration.md",
	"sourceDirName": "getting-started",
	"slug": "/getting-started/configuration",
	"permalink": "/getting-started/configuration",
	"draft": false,
	"unlisted": false,
	"tags": [],
	"version": "current",
	"sidebarPosition": 2,
	"frontMatter": {
		"sidebar_position": 2
	},
	"sidebar": "docs",
	"previous": {
		"title": "Installation",
		"permalink": "/getting-started/installation"
	},
	"next": {
		"title": "Project Structure",
		"permalink": "/getting-started/project-structure"
	}
}
